README.md
setup.py
pulumi_svmkit/__init__.py
pulumi_svmkit/_utilities.py
pulumi_svmkit/key_pair.py
pulumi_svmkit/provider.py
pulumi_svmkit/pulumi-plugin.json
pulumi_svmkit/py.typed
pulumi_svmkit.egg-info/PKG-INFO
pulumi_svmkit.egg-info/SOURCES.txt
pulumi_svmkit.egg-info/dependency_links.txt
pulumi_svmkit.egg-info/not-zip-safe
pulumi_svmkit.egg-info/requires.txt
pulumi_svmkit.egg-info/top_level.txt
pulumi_svmkit/account/__init__.py
pulumi_svmkit/account/stake_account.py
pulumi_svmkit/account/transfer.py
pulumi_svmkit/account/vote_account.py
pulumi_svmkit/agave/__init__.py
pulumi_svmkit/agave/_enums.py
pulumi_svmkit/agave/_inputs.py
pulumi_svmkit/agave/outputs.py
pulumi_svmkit/apt/__init__.py
pulumi_svmkit/apt/_inputs.py
pulumi_svmkit/apt/outputs.py
pulumi_svmkit/deb/__init__.py
pulumi_svmkit/deb/_inputs.py
pulumi_svmkit/deb/outputs.py
pulumi_svmkit/deletion/__init__.py
pulumi_svmkit/deletion/_enums.py
pulumi_svmkit/explorer/__init__.py
pulumi_svmkit/explorer/_inputs.py
pulumi_svmkit/explorer/explorer.py
pulumi_svmkit/explorer/outputs.py
pulumi_svmkit/faucet/__init__.py
pulumi_svmkit/faucet/_inputs.py
pulumi_svmkit/faucet/faucet.py
pulumi_svmkit/faucet/outputs.py
pulumi_svmkit/firedancer/__init__.py
pulumi_svmkit/firedancer/_enums.py
pulumi_svmkit/firedancer/_inputs.py
pulumi_svmkit/firedancer/outputs.py
pulumi_svmkit/firewall/__init__.py
pulumi_svmkit/firewall/_enums.py
pulumi_svmkit/firewall/_inputs.py
pulumi_svmkit/firewall/firewall.py
pulumi_svmkit/firewall/get_default_firewall_params.py
pulumi_svmkit/firewall/outputs.py
pulumi_svmkit/genesis/__init__.py
pulumi_svmkit/genesis/_inputs.py
pulumi_svmkit/genesis/outputs.py
pulumi_svmkit/genesis/solana.py
pulumi_svmkit/geyser/__init__.py
pulumi_svmkit/geyser/_inputs.py
pulumi_svmkit/geyser/outputs.py
pulumi_svmkit/machine/__init__.py
pulumi_svmkit/machine/machine.py
pulumi_svmkit/networkinfo/__init__.py
pulumi_svmkit/networkinfo/get_network_info.py
pulumi_svmkit/runner/__init__.py
pulumi_svmkit/runner/_inputs.py
pulumi_svmkit/runner/outputs.py
pulumi_svmkit/solana/__init__.py
pulumi_svmkit/solana/_enums.py
pulumi_svmkit/solana/_inputs.py
pulumi_svmkit/solana/outputs.py
pulumi_svmkit/ssh/__init__.py
pulumi_svmkit/ssh/_inputs.py
