Metadata-Version: 2.4
Name: pulumi_svmkit
Version: 0.48.0
Summary: SVMKit allows you to manage Solana SVM software components using infrastructure as code.
Home-page: https://abklabs.com
License: GPL-3.0-only
Project-URL: Repository, https://github.com/abklabs/pulumi-svmkit
Keywords: pulumi svmkit solana blockchain
Requires-Python: >=3.9
Requires-Dist: parver>=0.2.1
Requires-Dist: pulumi<4.0.0,>=3.165.0
Requires-Dist: semver>=2.8.1
Requires-Dist: typing-extensions<5,>=4.11; python_version < "3.11"
Dynamic: description
Dynamic: description-content-type
Dynamic: home-page
Dynamic: keywords
Dynamic: license
Dynamic: project-url
Dynamic: requires-dist
Dynamic: requires-python
Dynamic: summary
